[
    {
        "name": "黄金用户",
        "children": [
            {
                "name": "武汉",
                "value": [114.31, 30.52]
            },{
                "name": "天门",
                "value": [124.71, 40.13]
            },{
                "name": "湖南",
                "value": [114.81, 40.52]
            },{
                "name": "长沙",
                "value": [114.01, 22.63]
            }
        ]
    },{
        "name": "白金用户",
        "children": [
            {
                "name": "金华",
                "value": [84.31, 33.52]
            },{
                "name": "西安",
                "value": [94.71, 41.13]
            }
        ]
    },{
        "name": "黑铁用户",
        "children": [
            {
                "name": "成都",
                "value": [104.31, 30.67]
            }
        ]
    }
]